{"id":"dvf-2024-1228763","address":{"raw":"17 Rue Le Dantec, 75013 Paris","normalized":"17 Rue Le Dantec 75013 Paris","lat":48.828926,"lng":2.347311,"district":"75013"},"characteristics":{"surface_m2":50,"rooms":2,"floor":4},"pricing":{"current_price":547000,"price_per_m2":10940,"initial_price":547000},"timeline":{"first_seen":"2026-06-29","last_seen":"2026-07-02","days_on_market":3},"price_history":[{"date":"2026-06-29","price":547000,"source":"dvf"}],"status":"active","dvf":{"avg_price_m2_100m":8986,"avg_price_m2_500m":9134,"comparable_sales":[{"price":553150,"date":"2024-05-02","distance_m":29},{"price":250000,"date":"2024-09-23","distance_m":29},{"price":430510,"date":"2024-12-12","distance_m":29},{"price":367308,"date":"2024-02-16","distance_m":33},{"price":524000,"date":"2024-07-24","distance_m":33},{"price":367500,"date":"2024-10-28","distance_m":33},{"price":670000,"date":"2024-11-29","distance_m":33},{"price":128000,"date":"2024-02-23","distance_m":46}]},"risks":{"flood":0.08,"clay":0.53,"noise":0.55},"transport_score":69,"neighborhood":{"walk_score":83,"schools_500m":14,"income":27000,"velib_400m":6,"trees_150m":135,"amenities":{"food":14,"health":4,"green":2,"culture":4}},"rent":{"ref_m2":26.2,"max_m2":31.4,"min_m2":18.3,"quartier":"Maison-Blanche","monthly_est":1570},"investment":{"gross_yield":3.44,"net_yield":2.09,"ppm2_percentile":88,"negotiation_margin_pct":0.1,"dpe_risk_score":55,"value_add_flag":false},"pois":[{"type":"transport","lat":48.82979051369297,"lng":2.350414872010464,"label":"Corvisart · METRO 6"},{"type":"transport","lat":48.831129548026645,"lng":2.3435116577497763,"label":"Glacière · METRO 6"},{"type":"transport","lat":48.830972672988366,"lng":2.3555802740779104,"label":"Place d'Italie · METRO 5"},{"type":"transport","lat":48.83143363013256,"lng":2.355643643033711,"label":"Place d'Italie · METRO 7"},{"type":"transport","lat":48.8309272410005,"lng":2.356121938797104,"label":"Place d'Italie · METRO 6"},{"type":"park","lat":48.82879881542339,"lng":2.3496154437940278,"label":"JARDIN BRASSAI"},{"type":"park","lat":48.829683591378334,"lng":2.344877662756879,"label":"MAIL DE BIEVRE"},{"type":"park","lat":48.82786620943773,"lng":2.352148546553216,"label":"SQUARE HENRI ROUSSELLE"},{"type":"velib","lat":48.82758774190948,"lng":2.3492151126265526,"label":"Butte aux Cailles - Esperance"},{"type":"velib","lat":48.830981659316855,"lng":2.3481646925210953,"label":"Croulebarde - Corvisart"},{"type":"velib","lat":48.8300989,"lng":2.3502726,"label":"Auguste Blanqui - Corvisart"},{"type":"velib","lat":48.829522989420596,"lng":2.343570403754711,"label":"Glacière - Soeur Catherine Marie"}],"dpe":{"energy_class":"E","ghg_class":"E"},"images":["https://images.unsplash.com/photo-1502005097973-6a7082348e28?w=1200&h=750&q=66&auto=format&fit=crop&crop=entropy","https://images.unsplash.com/photo-1493663284031-b7e3aefcae8e?w=1200&h=750&q=66&auto=format&fit=crop&crop=entropy","https://images.unsplash.com/photo-1560448204-e02f11c3d0e2?w=1200&h=750&q=66&auto=format&fit=crop&crop=entropy","https://images.unsplash.com/photo-1484154218962-a197022b5858?w=1200&h=750&q=66&auto=format&fit=crop&crop=entropy","https://images.unsplash.com/photo-1540518614846-7eded433c457?w=1200&h=750&q=66&auto=format&fit=crop&crop=entropy"],"thumb":"https://images.unsplash.com/photo-1502005097973-6a7082348e28?w=480&h=300&q=55&auto=format&fit=crop&crop=entropy","score":{"opportunity_score":23,"value_score":12,"yield_score":35,"negotiation_score":1,"liquidity_score":68,"gentrification_score":48},"signals":{"price_drops":0,"total_drop_percent":0,"long_time_on_market":false,"explanations":["2.1% net rental yield (gross 3.4%)","20.9% above DVF average","3 days on market"]},"source":"dvf","url":"https://app.dvf.etalab.gouv.fr/"}