{"id":"dvf-2024-1209864","address":{"raw":"52 Rue Notre-Dame De Lorette, 75009 Paris","normalized":"52 Rue Notre-Dame de Lorette 75009 Paris","lat":48.87973,"lng":2.336079,"district":"75009"},"characteristics":{"surface_m2":20,"rooms":1,"floor":1},"pricing":{"current_price":170000,"price_per_m2":8500,"initial_price":170000},"timeline":{"first_seen":"2026-06-29","last_seen":"2026-07-02","days_on_market":3},"price_history":[{"date":"2026-06-29","price":170000,"source":"dvf"}],"status":"active","dvf":{"avg_price_m2_100m":11325,"avg_price_m2_500m":11421,"comparable_sales":[{"price":202000,"date":"2024-06-04","distance_m":21},{"price":376700,"date":"2024-01-24","distance_m":28},{"price":325000,"date":"2024-12-19","distance_m":44},{"price":1223900,"date":"2024-02-15","distance_m":46},{"price":1730000,"date":"2024-01-31","distance_m":49},{"price":456650,"date":"2024-02-06","distance_m":49},{"price":104000,"date":"2024-05-17","distance_m":49},{"price":1145000,"date":"2024-09-23","distance_m":56}]},"risks":{"flood":0.05,"clay":0.39,"noise":0.6},"transport_score":95,"neighborhood":{"walk_score":77,"schools_500m":12,"income":34000,"velib_400m":11,"trees_150m":32,"amenities":{"food":22,"health":14,"green":2,"culture":1}},"rent":{"ref_m2":31.1,"max_m2":37.3,"min_m2":21.8,"quartier":"Saint-Georges","monthly_est":746},"investment":{"gross_yield":5.27,"net_yield":3.78,"ppm2_percentile":14,"negotiation_margin_pct":0.1,"dpe_risk_score":10,"value_add_flag":false},"pois":[{"type":"transport","lat":48.87817339105656,"lng":2.337857510381017,"label":"Saint-Georges · METRO 12"},{"type":"transport","lat":48.88224953318808,"lng":2.3371645394451463,"label":"Pigalle · METRO 12"},{"type":"transport","lat":48.88222543392857,"lng":2.3382334685046176,"label":"Pigalle · METRO 2"},{"type":"transport","lat":48.876047496005405,"lng":2.337495844533765,"label":"Notre-Dame-de-Lorette · METRO 12"},{"type":"transport","lat":48.87633026495961,"lng":2.333108893760544,"label":"Trinité d'Estienne d'Orves · METRO 12"},{"type":"park","lat":48.878495609390626,"lng":2.3367433792051573,"label":"SQUARE ALEX BISCARRE"},{"type":"park","lat":48.878386938089356,"lng":2.3372525341755344,"label":"JARDIN DE LA BIBLIOTHEQUE THIERS (FONDATION DOSNE)"},{"type":"park","lat":48.88146670412989,"lng":2.332378524250056,"label":"JARDIN PAULINE GARCIA VIARDOT DE LA BIBLIOTHEQUE"},{"type":"velib","lat":48.87929591733507,"lng":2.3373600840568547,"label":"Toudouze - Clauzel"},{"type":"velib","lat":48.8811043724,"lng":2.3366955667734,"label":"Victor Massé - Jean-Baptiste Pigalle"},{"type":"velib","lat":48.87939826447722,"lng":2.333709173337285,"label":"Jean-Baptiste Pigalle - La Bruyere"},{"type":"velib","lat":48.87778639599673,"lng":2.337429821491241,"label":"Saint Georges - d'Aumale"}],"dpe":{"energy_class":"G","ghg_class":"C"},"images":["https://images.unsplash.com/photo-1493663284031-b7e3aefcae8e?w=1200&h=750&q=66&auto=format&fit=crop&crop=entropy","https://images.unsplash.com/photo-1540518614846-7eded433c457?w=1200&h=750&q=66&auto=format&fit=crop&crop=entropy","https://images.unsplash.com/photo-1502672260266-1c1ef2d93688?w=1200&h=750&q=66&auto=format&fit=crop&crop=entropy","https://images.unsplash.com/photo-1560448204-e02f11c3d0e2?w=1200&h=750&q=66&auto=format&fit=crop&crop=entropy","https://images.unsplash.com/photo-1556912173-3bb406ef7e77?w=1200&h=750&q=66&auto=format&fit=crop&crop=entropy"],"thumb":"https://images.unsplash.com/photo-1493663284031-b7e3aefcae8e?w=480&h=300&q=55&auto=format&fit=crop&crop=entropy","score":{"opportunity_score":43,"value_score":100,"yield_score":100,"negotiation_score":1,"liquidity_score":83,"gentrification_score":48},"signals":{"price_drops":0,"total_drop_percent":0,"long_time_on_market":false,"explanations":["3.8% net rental yield (gross 5.3%)","25.2% below DVF average (11 363 €/m²)","Cheaper than 86% of the arrondissement","3 days on market","Energy class G — rental restrictions apply"]},"source":"dvf","url":"https://app.dvf.etalab.gouv.fr/"}