{"id":"dvf-2024-1210282","address":{"raw":"4 Z 20, 75020 Paris","normalized":"4 Voie Z/20 75020 Paris","lat":48.874314,"lng":2.397291,"district":"75020"},"characteristics":{"surface_m2":92,"rooms":2,"floor":2},"pricing":{"current_price":854150,"price_per_m2":9284,"initial_price":854150},"timeline":{"first_seen":"2026-06-29","last_seen":"2026-07-01","days_on_market":2},"price_history":[{"date":"2026-06-29","price":854150,"source":"dvf"}],"status":"active","dvf":{"avg_price_m2_100m":8087,"avg_price_m2_500m":8131,"comparable_sales":[{"price":550000,"date":"2024-01-10","distance_m":32},{"price":410000,"date":"2024-05-24","distance_m":32},{"price":438000,"date":"2024-06-28","distance_m":32},{"price":342857,"date":"2024-03-18","distance_m":65},{"price":560150,"date":"2024-09-04","distance_m":66},{"price":523600,"date":"2024-09-12","distance_m":66},{"price":485000,"date":"2024-10-30","distance_m":66},{"price":150000,"date":"2024-02-08","distance_m":75}]},"risks":{"flood":0.07,"clay":0.41,"noise":0.4},"transport_score":98,"neighborhood":{"walk_score":91,"schools_500m":25,"income":25000,"velib_400m":4,"trees_150m":82,"amenities":{"food":22,"health":7,"green":2,"culture":5}},"rent":{"ref_m2":23.4,"max_m2":28.1,"min_m2":16.4,"quartier":"Saint-Fargeau","monthly_est":2585},"investment":{"gross_yield":3.63,"net_yield":2.26,"ppm2_percentile":70,"negotiation_margin_pct":0.1,"dpe_risk_score":75,"value_add_flag":false},"pois":[{"type":"transport","lat":48.87547445667917,"lng":2.398867596625601,"label":"Télégraphe · METRO 11"},{"type":"transport","lat":48.8768063892129,"lng":2.3930560919606623,"label":"Place des Fêtes · METRO 11"},{"type":"transport","lat":48.87694984811022,"lng":2.3929839648173936,"label":"Place des Fêtes · METRO 7bis"},{"type":"transport","lat":48.87511181695599,"lng":2.389415032035528,"label":"Jourdain · METRO 11"},{"type":"transport","lat":48.87210144213156,"lng":2.4045149423791043,"label":"Saint-Fargeau · METRO 3bis"},{"type":"park","lat":48.873377736123075,"lng":2.3962629691585597,"label":"JARDIN MARIO SOARES"},{"type":"park","lat":48.87548492267893,"lng":2.3965351966087907,"label":"JARDINIERES BELLEVILLE CONTRE ALLEE TELEGRAPHE"},{"type":"park","lat":48.87442420884051,"lng":2.3953475032399973,"label":"JARDIN LEON ZYGUEL"},{"type":"velib","lat":48.8736824,"lng":2.3960278,"label":"Square de la rue Pixérécourt"},{"type":"velib","lat":48.8756045,"lng":2.3995549,"label":"Belleville - Télégraphe"},{"type":"velib","lat":48.87330497045532,"lng":2.4014145880937576,"label":"Borrégo - Gambetta"},{"type":"velib","lat":48.875565910073,"lng":2.3930460959673,"label":"Belleville -  Pré Saint-Gervais"}],"dpe":{"energy_class":"D","ghg_class":"B"},"images":["https://images.unsplash.com/photo-1567496898669-ee935f5f647a?w=1200&h=750&q=66&auto=format&fit=crop&crop=entropy","https://images.unsplash.com/photo-1493663284031-b7e3aefcae8e?w=1200&h=750&q=66&auto=format&fit=crop&crop=entropy","https://images.unsplash.com/photo-1560448204-e02f11c3d0e2?w=1200&h=750&q=66&auto=format&fit=crop&crop=entropy","https://images.unsplash.com/photo-1505691938895-1758d7feb511?w=1200&h=750&q=66&auto=format&fit=crop&crop=entropy","https://images.unsplash.com/photo-1502672260266-1c1ef2d93688?w=1200&h=750&q=66&auto=format&fit=crop&crop=entropy"],"thumb":"https://images.unsplash.com/photo-1567496898669-ee935f5f647a?w=480&h=300&q=55&auto=format&fit=crop&crop=entropy","score":{"opportunity_score":33,"value_score":30,"yield_score":44,"negotiation_score":0,"liquidity_score":70,"gentrification_score":45},"signals":{"price_drops":0,"total_drop_percent":0,"long_time_on_market":false,"explanations":["2.3% net rental yield (gross 3.6%)","14.6% above DVF average","2 days on market"]},"source":"dvf","url":"https://app.dvf.etalab.gouv.fr/"}