{"id":"dvf-2024-1209954","address":{"raw":"44 Rue Jean-Baptiste Pigalle, 75009 Paris","normalized":"44 Rue Jean-Baptiste Pigalle 75009 Paris","lat":48.880132,"lng":2.33473,"district":"75009"},"characteristics":{"surface_m2":33,"rooms":2,"floor":1},"pricing":{"current_price":353500,"price_per_m2":10712,"initial_price":353500},"timeline":{"first_seen":"2026-06-29","last_seen":"2026-07-01","days_on_market":2},"price_history":[{"date":"2026-06-29","price":353500,"source":"dvf"}],"status":"active","dvf":{"avg_price_m2_100m":11544,"avg_price_m2_500m":11197,"comparable_sales":[{"price":130000,"date":"2024-06-27","distance_m":20},{"price":1057210,"date":"2024-06-07","distance_m":50},{"price":119000,"date":"2024-02-08","distance_m":54},{"price":712950,"date":"2024-02-22","distance_m":58},{"price":140000,"date":"2024-12-10","distance_m":58},{"price":1098000,"date":"2024-05-13","distance_m":61},{"price":635000,"date":"2024-12-12","distance_m":64},{"price":227053,"date":"2024-07-08","distance_m":65}]},"risks":{"flood":0.08,"clay":0.44,"noise":0.52},"transport_score":90,"neighborhood":{"walk_score":87,"schools_500m":11,"income":34000,"velib_400m":8,"trees_150m":108,"amenities":{"food":18,"health":3,"green":3,"culture":4}},"rent":{"ref_m2":26.7,"max_m2":32,"min_m2":18.7,"quartier":"Saint-Georges","monthly_est":1056},"investment":{"gross_yield":3.58,"net_yield":2.22,"ppm2_percentile":42,"negotiation_margin_pct":0.1,"dpe_risk_score":30,"value_add_flag":false},"pois":[{"type":"transport","lat":48.88224953318808,"lng":2.3371645394451463,"label":"Pigalle · METRO 12"},{"type":"transport","lat":48.87817339105656,"lng":2.337857510381017,"label":"Saint-Georges · METRO 12"},{"type":"transport","lat":48.88222543392857,"lng":2.3382334685046176,"label":"Pigalle · METRO 2"},{"type":"transport","lat":48.88355629016869,"lng":2.3333796724221587,"label":"Blanche · METRO 2"},{"type":"transport","lat":48.87633026495961,"lng":2.333108893760544,"label":"Trinité d'Estienne d'Orves · METRO 12"},{"type":"park","lat":48.88146670412989,"lng":2.332378524250056,"label":"JARDIN PAULINE GARCIA VIARDOT DE LA BIBLIOTHEQUE"},{"type":"park","lat":48.878495609390626,"lng":2.3367433792051573,"label":"SQUARE ALEX BISCARRE"},{"type":"park","lat":48.878386938089356,"lng":2.3372525341755344,"label":"JARDIN DE LA BIBLIOTHEQUE THIERS (FONDATION DOSNE)"},{"type":"velib","lat":48.87939826447722,"lng":2.333709173337285,"label":"Jean-Baptiste Pigalle - La Bruyere"},{"type":"velib","lat":48.8811043724,"lng":2.3366955667734,"label":"Victor Massé - Jean-Baptiste Pigalle"},{"type":"velib","lat":48.87929591733507,"lng":2.3373600840568547,"label":"Toudouze - Clauzel"},{"type":"velib","lat":48.882291011481,"lng":2.3332412168384,"label":"Douai - Pierre Fontaine"}],"dpe":{"energy_class":"F","ghg_class":"C"},"images":["https://images.unsplash.com/photo-1554995207-c18c203602cb?w=1200&h=750&q=66&auto=format&fit=crop&crop=entropy","https://images.unsplash.com/photo-1505691938895-1758d7feb511?w=1200&h=750&q=66&auto=format&fit=crop&crop=entropy","https://images.unsplash.com/photo-1522708323590-d24dbb6b0267?w=1200&h=750&q=66&auto=format&fit=crop&crop=entropy","https://images.unsplash.com/photo-1502672260266-1c1ef2d93688?w=1200&h=750&q=66&auto=format&fit=crop&crop=entropy","https://images.unsplash.com/photo-1567496898669-ee935f5f647a?w=1200&h=750&q=66&auto=format&fit=crop&crop=entropy"],"thumb":"https://images.unsplash.com/photo-1554995207-c18c203602cb?w=480&h=300&q=55&auto=format&fit=crop&crop=entropy","score":{"opportunity_score":32,"value_score":65,"yield_score":41,"negotiation_score":0,"liquidity_score":84,"gentrification_score":48},"signals":{"price_drops":0,"total_drop_percent":0,"long_time_on_market":false,"explanations":["2.2% net rental yield (gross 3.6%)","6.1% below DVF average (11 405 €/m²)","2 days on market","Energy class F — rental restrictions apply"]},"source":"dvf","url":"https://app.dvf.etalab.gouv.fr/"}