{"id":"dvf-2024-1210367","address":{"raw":"73 Rue De Caumartin, 75009 Paris","normalized":"73 Rue de Caumartin 75009 Paris","lat":48.875462,"lng":2.328413,"district":"75009"},"characteristics":{"surface_m2":120,"rooms":6,"floor":7},"pricing":{"current_price":1515000,"price_per_m2":12625,"initial_price":1515000},"timeline":{"first_seen":"2026-06-29","last_seen":"2026-07-01","days_on_market":2},"price_history":[{"date":"2026-06-29","price":1515000,"source":"dvf"}],"status":"active","dvf":{"avg_price_m2_100m":11187,"avg_price_m2_500m":11359,"comparable_sales":[{"price":460000,"date":"2024-01-29","distance_m":93},{"price":340000,"date":"2024-10-17","distance_m":93},{"price":465000,"date":"2024-11-27","distance_m":95},{"price":270000,"date":"2024-06-20","distance_m":118},{"price":225000,"date":"2024-07-17","distance_m":132},{"price":566000,"date":"2024-09-06","distance_m":189},{"price":270000,"date":"2024-12-12","distance_m":189},{"price":198104,"date":"2024-12-23","distance_m":189}]},"risks":{"flood":0.06,"clay":0.25,"noise":0.5},"transport_score":100,"neighborhood":{"walk_score":53,"schools_500m":9,"income":34000,"velib_400m":12,"trees_150m":58,"amenities":{"food":5,"health":0,"green":0,"culture":7}},"rent":{"ref_m2":26.4,"max_m2":31.7,"min_m2":18.5,"quartier":"Chaussée-d'Antin","monthly_est":3804},"investment":{"gross_yield":3.01,"net_yield":1.69,"ppm2_percentile":74,"negotiation_margin_pct":0.1,"dpe_risk_score":75,"value_add_flag":false},"pois":[{"type":"transport","lat":48.87567210708072,"lng":2.3278422352596215,"label":"Saint-Lazare · METRO 12"},{"type":"transport","lat":48.8750292564036,"lng":2.3267224755800515,"label":"Haussmann-Saint-Lazare · RER E"},{"type":"transport","lat":48.87371340670775,"lng":2.3276954096301736,"label":"Havre-Caumartin · METRO 9"},{"type":"transport","lat":48.87542071665263,"lng":2.32547637444705,"label":"Saint-Lazare · METRO 13"},{"type":"transport","lat":48.873513389595466,"lng":2.3275430817269713,"label":"Havre-Caumartin · METRO 3"},{"type":"park","lat":48.87674498790556,"lng":2.3316282200485166,"label":"SQUARE D'ESTIENNE D'ORVES"},{"type":"park","lat":48.87381991558385,"lng":2.3232157507919675,"label":"SQUARE LOUIS XVI"},{"type":"velib","lat":48.874422773426545,"lng":2.3284685611724854,"label":"Caumartin - Provence"},{"type":"velib","lat":48.875674400851,"lng":2.3265598341823,"label":"Gare Saint-Lazare - Cour du Havre"},{"type":"velib","lat":48.874777677621296,"lng":2.326515804784655,"label":"Gare Saint-Lazare - Isly"},{"type":"velib","lat":48.876693805756986,"lng":2.3305362090468407,"label":"Londres - Place d'Estienne d'Orves"}],"dpe":{"energy_class":"D","ghg_class":"D"},"images":["https://images.unsplash.com/photo-1484154218962-a197022b5858?w=1200&h=750&q=66&auto=format&fit=crop&crop=entropy","https://images.unsplash.com/photo-1493809842364-78817add7ffb?w=1200&h=750&q=66&auto=format&fit=crop&crop=entropy","https://images.unsplash.com/photo-1502005097973-6a7082348e28?w=1200&h=750&q=66&auto=format&fit=crop&crop=entropy","https://images.unsplash.com/photo-1502672260266-1c1ef2d93688?w=1200&h=750&q=66&auto=format&fit=crop&crop=entropy","https://images.unsplash.com/photo-1556912173-3bb406ef7e77?w=1200&h=750&q=66&auto=format&fit=crop&crop=entropy"],"thumb":"https://images.unsplash.com/photo-1484154218962-a197022b5858?w=480&h=300&q=55&auto=format&fit=crop&crop=entropy","score":{"opportunity_score":23,"value_score":26,"yield_score":14,"negotiation_score":0,"liquidity_score":67,"gentrification_score":48},"signals":{"price_drops":0,"total_drop_percent":0,"long_time_on_market":false,"explanations":["1.7% net rental yield (gross 3.0%)","12.2% above DVF average","2 days on market"]},"source":"dvf","url":"https://app.dvf.etalab.gouv.fr/"}