{"id":"dvf-2024-1228976","address":{"raw":"8 Rue Cdt Schloesing, 75016 Paris","normalized":"8 Rue du Commandant Schloesing 75016 Paris","lat":48.861827,"lng":2.284151,"district":"75016"},"characteristics":{"surface_m2":139,"rooms":4,"floor":0},"pricing":{"current_price":1520580,"price_per_m2":10939,"initial_price":1520580},"timeline":{"first_seen":"2026-06-29","last_seen":"2026-07-01","days_on_market":2},"price_history":[{"date":"2026-06-29","price":1520580,"source":"dvf"}],"status":"active","dvf":{"avg_price_m2_100m":10992,"avg_price_m2_500m":12084,"comparable_sales":[{"price":443800,"date":"2024-07-11","distance_m":22},{"price":250000,"date":"2024-09-05","distance_m":22},{"price":1349000,"date":"2024-04-09","distance_m":28},{"price":1788873,"date":"2024-07-04","distance_m":28},{"price":500000,"date":"2024-11-12","distance_m":28},{"price":670830,"date":"2024-03-28","distance_m":63},{"price":689700,"date":"2024-04-17","distance_m":75},{"price":360000,"date":"2024-08-20","distance_m":75}]},"risks":{"flood":0.1,"clay":0.44,"noise":0.51},"transport_score":88,"neighborhood":{"walk_score":49,"schools_500m":10,"income":44000,"velib_400m":4,"trees_150m":40,"amenities":{"food":3,"health":6,"green":0,"culture":2}},"rent":{"ref_m2":25.2,"max_m2":30.2,"min_m2":17.6,"quartier":"Muette","monthly_est":4198},"investment":{"gross_yield":3.31,"net_yield":1.97,"ppm2_percentile":64,"negotiation_margin_pct":0.1,"dpe_risk_score":55,"value_add_flag":false},"pois":[{"type":"transport","lat":48.863065020217945,"lng":2.2862431693282357,"label":"Trocadéro · METRO 9"},{"type":"transport","lat":48.863610937645674,"lng":2.2875801625296517,"label":"Trocadéro · METRO 6"},{"type":"transport","lat":48.86394013069539,"lng":2.2784416488331494,"label":"Rue de la Pompe · METRO 9"},{"type":"transport","lat":48.85744869007581,"lng":2.2858124441464076,"label":"Passy · METRO 6"},{"type":"transport","lat":48.86698310944948,"lng":2.290058833580487,"label":"Boissière · METRO 6"},{"type":"park","lat":48.862531506628414,"lng":2.285100122038995,"label":"CIMETIERE DE PASSY"},{"type":"park","lat":48.86164950866197,"lng":2.2864393297684313,"label":"SQUARE YORKTOWN"},{"type":"park","lat":48.86299506371672,"lng":2.2871278022085346,"label":"JARDIN DE LA PLACE DU TROCADERO ET DU ONZE NOVEMBRE"},{"type":"velib","lat":48.861773096259,"lng":2.2838841134601,"label":"Commandant Schloesing - Pétrarque"},{"type":"velib","lat":48.863354122371,"lng":2.2864209115505,"label":"Eylau - Trocadéro"},{"type":"velib","lat":48.863875,"lng":2.28189,"label":"Sablons - Georges Mandel"},{"type":"velib","lat":48.8584893,"lng":2.2839655,"label":"Passy - Place du Costa Rica"}],"dpe":{"energy_class":"E","ghg_class":"E"},"images":["https://images.unsplash.com/photo-1484154218962-a197022b5858?w=1200&h=750&q=66&auto=format&fit=crop&crop=entropy","https://images.unsplash.com/photo-1522708323590-d24dbb6b0267?w=1200&h=750&q=66&auto=format&fit=crop&crop=entropy","https://images.unsplash.com/photo-1502672260266-1c1ef2d93688?w=1200&h=750&q=66&auto=format&fit=crop&crop=entropy","https://images.unsplash.com/photo-1505691938895-1758d7feb511?w=1200&h=750&q=66&auto=format&fit=crop&crop=entropy","https://images.unsplash.com/photo-1554995207-c18c203602cb?w=1200&h=750&q=66&auto=format&fit=crop&crop=entropy"],"thumb":"https://images.unsplash.com/photo-1484154218962-a197022b5858?w=480&h=300&q=55&auto=format&fit=crop&crop=entropy","score":{"opportunity_score":33,"value_score":61,"yield_score":28,"negotiation_score":0,"liquidity_score":64,"gentrification_score":64},"signals":{"price_drops":0,"total_drop_percent":0,"long_time_on_market":false,"explanations":["2.0% net rental yield (gross 3.3%)","4.3% below DVF average (11 429 €/m²)","2 days on market"]},"source":"dvf","url":"https://app.dvf.etalab.gouv.fr/"}