{"id":"dvf-2024-1228978","address":{"raw":"38 Rue Gregoire De Tours, 75006 Paris","normalized":"38 Rue Grégoire de Tours 75006 Paris","lat":48.852187,"lng":2.337466,"district":"75006"},"characteristics":{"surface_m2":21,"rooms":1,"floor":1},"pricing":{"current_price":207400,"price_per_m2":9876,"initial_price":207400},"timeline":{"first_seen":"2026-06-29","last_seen":"2026-07-02","days_on_market":3},"price_history":[{"date":"2026-06-29","price":207400,"source":"dvf"}],"status":"active","dvf":{"avg_price_m2_100m":17473,"avg_price_m2_500m":16473,"comparable_sales":[{"price":1400000,"date":"2024-05-17","distance_m":20},{"price":1875000,"date":"2024-11-05","distance_m":37},{"price":262000,"date":"2024-04-05","distance_m":40},{"price":3156197,"date":"2024-11-04","distance_m":43},{"price":618500,"date":"2024-07-25","distance_m":50},{"price":3920600,"date":"2024-10-07","distance_m":53},{"price":600000,"date":"2024-01-03","distance_m":59},{"price":710000,"date":"2024-01-26","distance_m":66}]},"risks":{"flood":0.11,"clay":0.22,"noise":0.82},"transport_score":99,"neighborhood":{"walk_score":85,"schools_500m":10,"income":43000,"velib_400m":10,"trees_150m":51,"amenities":{"food":21,"health":4,"green":4,"culture":3}},"rent":{"ref_m2":34,"max_m2":40.8,"min_m2":23.8,"quartier":"Odeon","monthly_est":857},"investment":{"gross_yield":4.96,"net_yield":3.5,"ppm2_percentile":2,"negotiation_margin_pct":0.1,"dpe_risk_score":10,"value_add_flag":true},"pois":[{"type":"transport","lat":48.852300763094235,"lng":2.3397277815930964,"label":"Odéon · METRO 4"},{"type":"transport","lat":48.8530167679172,"lng":2.335502051727558,"label":"Mabillon · METRO 10"},{"type":"transport","lat":48.85193594203498,"lng":2.340613006406504,"label":"Odéon · METRO 10"},{"type":"transport","lat":48.853718934000206,"lng":2.3337761382184676,"label":"Saint-Germain-des-Prés · METRO 4"},{"type":"transport","lat":48.85316798489062,"lng":2.343285978923924,"label":"Saint-Michel · METRO 4"},{"type":"park","lat":48.85142545112204,"lng":2.338156317651731,"label":"JARDINET DU 6 RUE CONDE"},{"type":"park","lat":48.85371512804107,"lng":2.334597522096189,"label":"SQUARE FELIX DESRUELLES"},{"type":"park","lat":48.849520121107176,"lng":2.3376796364935615,"label":"SQUARE FRANCIS POULENC"},{"type":"velib","lat":48.851751374458864,"lng":2.338161695134053,"label":"Quatre Vents - Carrefour de l'Odéon"},{"type":"velib","lat":48.85165625855281,"lng":2.335500307381153,"label":"Marché Saint-Germain"},{"type":"velib","lat":48.85375581057431,"lng":2.3390958085656166,"label":"André Mazet - Saint-André des Arts"},{"type":"velib","lat":48.853305277595,"lng":2.3344654618827,"label":"Saint-Germain - Ciseaux"}],"dpe":{"energy_class":"G","ghg_class":"C"},"images":["https://images.unsplash.com/photo-1493663284031-b7e3aefcae8e?w=1200&h=750&q=66&auto=format&fit=crop&crop=entropy","https://images.unsplash.com/photo-1540518614846-7eded433c457?w=1200&h=750&q=66&auto=format&fit=crop&crop=entropy","https://images.unsplash.com/photo-1522708323590-d24dbb6b0267?w=1200&h=750&q=66&auto=format&fit=crop&crop=entropy","https://images.unsplash.com/photo-1502005097973-6a7082348e28?w=1200&h=750&q=66&auto=format&fit=crop&crop=entropy","https://images.unsplash.com/photo-1556912173-3bb406ef7e77?w=1200&h=750&q=66&auto=format&fit=crop&crop=entropy"],"thumb":"https://images.unsplash.com/photo-1493663284031-b7e3aefcae8e?w=480&h=300&q=55&auto=format&fit=crop&crop=entropy","score":{"opportunity_score":80,"value_score":100,"yield_score":100,"negotiation_score":1,"liquidity_score":97,"gentrification_score":48},"signals":{"price_drops":0,"total_drop_percent":0,"long_time_on_market":false,"explanations":["3.5% net rental yield (gross 5.0%)","42.2% below DVF average (17 073 €/m²)","Cheaper than 98% of the arrondissement","3 days on market","Value-add: discount exceeds renovation cost (F/G arbitrage)"]},"source":"dvf","url":"https://app.dvf.etalab.gouv.fr/"}